{
  "gap": {
    "xxs": {
      "value": 4,
      "type": "spacing",
      "unit": "px",
      "meta": {
        "description": "Extra extra small gap",
        "category": "spacing"
      }
    },
    "xs": {
      "value": 10,
      "type": "spacing",
      "unit": "px",
      "meta": {
        "description": "Extra small gap",
        "category": "spacing"
      }
    },
    "sm": {
      "value": 12,
      "type": "spacing",
      "unit": "px",
      "meta": {
        "description": "Small gap",
        "category": "spacing"
      }
    },
    "md": {
      "value": 14,
      "type": "spacing",
      "unit": "px",
      "meta": {
        "description": "Medium gap",
        "category": "spacing"
      }
    },
    "lg": {
      "value": 24,
      "type": "spacing",
      "unit": "px",
      "meta": {
        "description": "Large gap",
        "category": "spacing"
      }
    },
    "xl": {
      "value": 32,
      "type": "spacing",
      "unit": "px",
      "meta": {
        "description": "Extra large gap",
        "category": "spacing"
      }
    }
  },
  "outline": {
    "value": 1,
    "type": "border",
    "unit": "px",
    "meta": {
      "description": "Default outline width",
      "category": "border"
    }
  },
  "roundness": {
    "xxs": {
      "value": 4,
      "type": "radius",
      "unit": "px",
      "meta": {
        "description": "Extra extra small border radius",
        "category": "radius"
      }
    },
    "xs": {
      "value": 8,
      "type": "radius",
      "unit": "px",
      "meta": {
        "description": "Extra small border radius",
        "category": "radius"
      }
    },
    "sm": {
      "value": 12,
      "type": "radius",
      "unit": "px",
      "meta": {
        "description": "Small border radius",
        "category": "radius"
      }
    },
    "md": {
      "value": 16,
      "type": "radius",
      "unit": "px",
      "meta": {
        "description": "Medium border radius",
        "category": "radius"
      }
    },
    "lg": {
      "value": 20,
      "type": "radius",
      "unit": "px",
      "meta": {
        "description": "Large border radius",
        "category": "radius"
      }
    },
    "xl": {
      "value": 24,
      "type": "radius",
      "unit": "px",
      "meta": {
        "description": "Extra large border radius",
        "category": "radius"
      }
    },
    "xxl": {
      "value": 32,
      "type": "radius",
      "unit": "px",
      "meta": {
        "description": "Extra extra large border radius",
        "category": "radius"
      }
    },
    "infinity": {
      "value": 9999,
      "type": "radius",
      "unit": "px",
      "meta": {
        "description": "Fully rounded / pill shape",
        "category": "radius"
      }
    }
  },
  "spacing": {
    "xxs": {
      "value": 4,
      "type": "spacing",
      "unit": "px",
      "meta": {
        "description": "Extra extra small spacing",
        "category": "spacing"
      }
    },
    "xs": {
      "value": 8,
      "type": "spacing",
      "unit": "px",
      "meta": {
        "description": "Extra small spacing",
        "category": "spacing"
      }
    },
    "sm": {
      "value": 12,
      "type": "spacing",
      "unit": "px",
      "meta": {
        "description": "Small spacing",
        "category": "spacing"
      }
    },
    "md": {
      "value": 16,
      "type": "spacing",
      "unit": "px",
      "meta": {
        "description": "Medium spacing",
        "category": "spacing"
      }
    },
    "lg": {
      "value": 24,
      "type": "spacing",
      "unit": "px",
      "meta": {
        "description": "Large spacing",
        "category": "spacing"
      }
    },
    "xl": {
      "value": 32,
      "type": "spacing",
      "unit": "px",
      "meta": {
        "description": "Extra large spacing",
        "category": "spacing"
      }
    },
    "xxl": {
      "value": 48,
      "type": "spacing",
      "unit": "px",
      "meta": {
        "description": "Extra extra large spacing",
        "category": "spacing"
      }
    }
  },
  "stroke": {
    "sm": {
      "value": 1,
      "type": "border",
      "unit": "px",
      "meta": {
        "description": "Thin stroke width",
        "category": "border"
      }
    },
    "md": {
      "value": 2,
      "type": "border",
      "unit": "px",
      "meta": {
        "description": "Medium stroke width",
        "category": "border"
      }
    },
    "lg": {
      "value": 3,
      "type": "border",
      "unit": "px",
      "meta": {
        "description": "Large stroke width",
        "category": "border"
      }
    },
    "xl": {
      "value": 4,
      "type": "border",
      "unit": "px",
      "meta": {
        "description": "Extra large stroke width",
        "category": "border"
      }
    }
  },
  "touchArea": {
    "sm": {
      "size": {
        "value": 36,
        "type": "size",
        "unit": "px",
        "meta": {
          "description": "Small touch target area",
          "category": "size"
        }
      }
    }
  }
}