{
  "neutral": {
    "primary": {
      "background": {
        "normal": {
          "value": "{themes.themes.light.background.primary.value}",
          "type": "color",
          "unit": "hex",
          "meta": {
            "category": "main header"
          }
        }
      }
    }
  },
  "accent": {
    "primary": {
      "background": {
        "normal": {
          "value": "{themes.themes.light.background.accent.value}",
          "type": "color",
          "unit": "hex",
          "meta": {
            "category": "main header"
          }
        }
      }
    }
  }
}
